margemliquida_market_data/__init__.py
margemliquida_market_data/anbima/__init__.py
margemliquida_market_data/anbima/anbima.py
margemliquida_market_data/b3/__init__.py
margemliquida_market_data/b3/b3.py
margemliquida_market_data/b3/bdrs.py
margemliquida_market_data/b3/etfs.py
margemliquida_market_data/b3/listas.py
margemliquida_market_data/bcb/__init__.py
margemliquida_market_data/bcb/bcb.py
margemliquida_market_data/carteira_global/__init__.py
margemliquida_market_data/carteira_global/carteira_global.py
margemliquida_market_data/cvm/__init__.py
margemliquida_market_data/cvm/cvm.py
margemliquida_market_data/fundsexplorer/__init__.py
margemliquida_market_data/fundsexplorer/fundsexplorer.py
margemliquida_market_data/ibge/__init__.py
margemliquida_market_data/ibge/ibge.py
margemliquida_market_data/maisretorno/bdrs.py
margemliquida_market_data/maisretorno/lista_bdrs.py
margemliquida_market_data/maisretorno/teste.py
margemliquida_market_data/meu_fundamentus/__init__.py
margemliquida_market_data/meu_fundamentus/meu_fundamentus.py
margemliquida_market_data/meu_fundamentus/utils.py
margemliquida_market_data/nasdaq/__init__.py
margemliquida_market_data/nasdaq/nasdaq.py
margemliquida_market_data/selenium_config/__init__.py
margemliquida_market_data/selenium_config/meu_firefox.py
margemliquida_market_data/tesouro_transparente/__init__.py
margemliquida_market_data/tesouro_transparente/tesouro_transparente.py
margemliquida_market_data/teste_gustavo_correa.py
margemliquida_market_data/teste_gustavo_correa2.py
margemliquida_market_data/yfinance/__init__.py
margemliquida_market_data/yfinance/yfinance.py
margemliquida_market_data-0.1.7.dist-info/LICENSE
margemliquida_market_data-0.1.7.dist-info/METADATA
margemliquida_market_data-0.1.7.dist-info/WHEEL
margemliquida_market_data-0.1.7.dist-info/RECORD
