Metadata-Version: 2.1
Name: margemliquida-market-data
Version: 0.1.7
Summary: Biblioteca utilitária para obtenção de dados do mercado financeiro
License: MIT
Author: Pablo Souza Grigoletti
Author-email: psgrigoletti@gmail.com
Requires-Python: ==3.11.*
Classifier: Development Status :: 1 - Planning
Classifier: License :: OSI Approved :: MIT License
Classifier: Natural Language :: Portuguese (Brazilian)
Classifier: Programming Language :: Python :: 3
Classifier: Programming Language :: Python :: 3.11
Classifier: Topic :: Office/Business :: Financial
Classifier: Topic :: Software Development :: Libraries
Requires-Dist: fundamentus (==0.2.0)
Requires-Dist: matplotlib (==3.8.2)
Requires-Dist: numpy (>=1.26.3,<2.0.0)
Requires-Dist: pandas (==2.1.4)
Requires-Dist: pip (>=23.3.2,<24.0.0)
Requires-Dist: python-bcb (>=0.2.0,<0.3.0)
Requires-Dist: redis (==5.0.1)
Requires-Dist: selenium (>=4.16.0,<5.0.0)
Requires-Dist: sidrapy (>=0.1.4,<0.2.0)
Requires-Dist: yfinance (==0.2.35)
Project-URL: Bug Tracker, https://github.com/psgrigoletti/margemliquida-market-data/issues
Project-URL: Código, https://github.com/psgrigoletti/margemliquida-market-data
Project-URL: Documentação, https://margemliquida-market-data.readthedocs.io/pt/latest/
